[{"uid": "92aa669f-1e40-43df-adbf-29462decf2d8", "bot": false, "x": 268.81, "y": 110.42, "z": -47.45, "ts": 1770767616, "e": "Position"}, {"uid": "92aa669f-1e40-43df-adbf-29462decf2d8", "bot": false, "x": 236.38, "y": 110.41, "z": -51.91, "ts": 1770767632, "e": "Position"}, {"uid": "92aa669f-1e40-43df-adbf-29462decf2d8", "bot": false, "x": 248.84, "y": 110.41, "z": -50.04, "ts": 1770767637, "e": "Position"}, {"uid": "92aa669f-1e40-43df-adbf-29462decf2d8", "bot": false, "x": 264.88, "y": 110.43, "z": -48.21, "ts": 1770767642, "e": "Position"}, {"uid": "92aa669f-1e40-43df-adbf-29462decf2d8", "bot": false, "x": 244.76, "y": 110.43, "z": -51.32, "ts": 1770767647, "e": "Position"}, {"uid": "92aa669f-1e40-43df-adbf-29462decf2d8", "bot": false, "x": 240.86, "y": 110.16, "z": -79.09, "ts": 1770767652, "e": "Position"}, {"uid": "92aa669f-1e40-43df-adbf-29462decf2d8", "bot": false, "x": 227.55, "y": 111.49, "z": -106.48, "ts": 1770767657, "e": "Position"}, {"uid": "92aa669f-1e40-43df-adbf-29462decf2d8", "bot": false, "x": 228.38, "y": 110.64, "z": -121.24, "ts": 1770767662, "e": "Position"}, {"uid": "92aa669f-1e40-43df-adbf-29462decf2d8", "bot": false, "x": 224.52, "y": 110.84, "z": -137.18, "ts": 1770767667, "e": "Position"}, {"uid": "92aa669f-1e40-43df-adbf-29462decf2d8", "bot": false, "x": 213.89, "y": 111.53, "z": -145.95, "ts": 1770767672, "e": "Position"}, {"uid": "92aa669f-1e40-43df-adbf-29462decf2d8", "bot": false, "x": 203.86, "y": 112.0, "z": -158.59, "ts": 1770767677, "e": "Position"}, {"uid": "92aa669f-1e40-43df-adbf-29462decf2d8", "bot": false, "x": 192.27, "y": 114.29, "z": -181.98, "ts": 1770767682, "e": "Position"}, {"uid": "92aa669f-1e40-43df-adbf-29462decf2d8", "bot": false, "x": 173.08, "y": 117.67, "z": -205.76, "ts": 1770767687, "e": "Position"}, {"uid": "92aa669f-1e40-43df-adbf-29462decf2d8", "bot": false, "x": 167.35, "y": 122.25, "z": -227.01, "ts": 1770767692, "e": "Position"}, {"uid": "92aa669f-1e40-43df-adbf-29462decf2d8", "bot": false, "x": 142.92, "y": 122.93, "z": -225.02, "ts": 1770767697, "e": "Position"}, {"uid": "92aa669f-1e40-43df-adbf-29462decf2d8", "bot": false, "x": 147.43, "y": 125.79, "z": -245.83, "ts": 1770767702, "e": "Position"}, {"uid": "92aa669f-1e40-43df-adbf-29462decf2d8", "bot": false, "x": 161.38, "y": 127.01, "z": -253.29, "ts": 1770767707, "e": "Position"}, {"uid": "92aa669f-1e40-43df-adbf-29462decf2d8", "bot": false, "x": 173.81, "y": 128.12, "z": -249.28, "ts": 1770767712, "e": "Position"}, {"uid": "92aa669f-1e40-43df-adbf-29462decf2d8", "bot": false, "x": 188.28, "y": 128.88, "z": -247.72, "ts": 1770767717, "e": "Position"}, {"uid": "92aa669f-1e40-43df-adbf-29462decf2d8", "bot": false, "x": 194.85, "y": 128.98, "z": -253.92, "ts": 1770767722, "e": "Position"}, {"uid": "92aa669f-1e40-43df-adbf-29462decf2d8", "bot": false, "x": 200.25, "y": 128.98, "z": -254.36, "ts": 1770767726, "e": "Loot"}, {"uid": "92aa669f-1e40-43df-adbf-29462decf2d8", "bot": false, "x": 200.25, "y": 128.98, "z": -254.36, "ts": 1770767727, "e": "Position"}, {"uid": "92aa669f-1e40-43df-adbf-29462decf2d8", "bot": false, "x": 183.65, "y": 128.83, "z": -254.95, "ts": 1770767732, "e": "Position"}, {"uid": "92aa669f-1e40-43df-adbf-29462decf2d8", "bot": false, "x": 178.1, "y": 128.72, "z": -273.05, "ts": 1770767737, "e": "Position"}, {"uid": "92aa669f-1e40-43df-adbf-29462decf2d8", "bot": false, "x": 180.39, "y": 128.63, "z": -283.87, "ts": 1770767742, "e": "Position"}, {"uid": "92aa669f-1e40-43df-adbf-29462decf2d8", "bot": false, "x": 174.84, "y": 128.79, "z": -293.82, "ts": 1770767747, "e": "Position"}, {"uid": "92aa669f-1e40-43df-adbf-29462decf2d8", "bot": false, "x": 166.16, "y": 128.79, "z": -288.7, "ts": 1770767752, "e": "Loot"}, {"uid": "92aa669f-1e40-43df-adbf-29462decf2d8", "bot": false, "x": 166.16, "y": 128.79, "z": -288.7, "ts": 1770767752, "e": "Loot"}, {"uid": "92aa669f-1e40-43df-adbf-29462decf2d8", "bot": false, "x": 166.16, "y": 128.79, "z": -288.7, "ts": 1770767752, "e": "Position"}, {"uid": "92aa669f-1e40-43df-adbf-29462decf2d8", "bot": false, "x": 175.25, "y": 128.79, "z": -298.55, "ts": 1770767757, "e": "Position"}, {"uid": "92aa669f-1e40-43df-adbf-29462decf2d8", "bot": false, "x": 175.78, "y": 128.79, "z": -300.04, "ts": 1770767759, "e": "Loot"}, {"uid": "92aa669f-1e40-43df-adbf-29462decf2d8", "bot": false, "x": 173.38, "y": 128.79, "z": -305.72, "ts": 1770767762, "e": "Position"}, {"uid": "92aa669f-1e40-43df-adbf-29462decf2d8", "bot": false, "x": 161.83, "y": 128.38, "z": -311.66, "ts": 1770767772, "e": "Position"}, {"uid": "92aa669f-1e40-43df-adbf-29462decf2d8", "bot": false, "x": 148.13, "y": 128.4, "z": -327.72, "ts": 1770767777, "e": "Position"}, {"uid": "92aa669f-1e40-43df-adbf-29462decf2d8", "bot": false, "x": 121.16, "y": 128.35, "z": -337.17, "ts": 1770767782, "e": "Position"}, {"uid": "92aa669f-1e40-43df-adbf-29462decf2d8", "bot": false, "x": 94.2, "y": 127.3, "z": -336.97, "ts": 1770767787, "e": "Position"}, {"uid": "92aa669f-1e40-43df-adbf-29462decf2d8", "bot": false, "x": 72.1, "y": 126.37, "z": -327.85, "ts": 1770767792, "e": "Position"}, {"uid": "92aa669f-1e40-43df-adbf-29462decf2d8", "bot": false, "x": 75.9, "y": 126.37, "z": -319.68, "ts": 1770767797, "e": "Position"}, {"uid": "92aa669f-1e40-43df-adbf-29462decf2d8", "bot": false, "x": 79.82, "y": 126.1, "z": -299.6, "ts": 1770767803, "e": "Position"}, {"uid": "92aa669f-1e40-43df-adbf-29462decf2d8", "bot": false, "x": 76.61, "y": 125.87, "z": -291.37, "ts": 1770767808, "e": "Position"}, {"uid": "92aa669f-1e40-43df-adbf-29462decf2d8", "bot": false, "x": 61.65, "y": 124.87, "z": -280.8, "ts": 1770767818, "e": "Position"}, {"uid": "92aa669f-1e40-43df-adbf-29462decf2d8", "bot": false, "x": 62.05, "y": 124.91, "z": -279.15, "ts": 1770767823, "e": "Position"}, {"uid": "92aa669f-1e40-43df-adbf-29462decf2d8", "bot": false, "x": 70.67, "y": 125.26, "z": -274.41, "ts": 1770767828, "e": "Position"}, {"uid": "92aa669f-1e40-43df-adbf-29462decf2d8", "bot": false, "x": 77.89, "y": 126.37, "z": -287.29, "ts": 1770767833, "e": "Position"}, {"uid": "92aa669f-1e40-43df-adbf-29462decf2d8", "bot": false, "x": 85.77, "y": 126.32, "z": -304.03, "ts": 1770767838, "e": "Position"}, {"uid": "92aa669f-1e40-43df-adbf-29462decf2d8", "bot": false, "x": 89.29, "y": 126.37, "z": -308.22, "ts": 1770767843, "e": "Position"}, {"uid": "92aa669f-1e40-43df-adbf-29462decf2d8", "bot": false, "x": 90.95, "y": 126.43, "z": -306.55, "ts": 1770767848, "e": "Position"}, {"uid": "92aa669f-1e40-43df-adbf-29462decf2d8", "bot": false, "x": 91.02, "y": 126.43, "z": -322.86, "ts": 1770767858, "e": "Position"}, {"uid": "92aa669f-1e40-43df-adbf-29462decf2d8", "bot": false, "x": 97.3, "y": 126.54, "z": -323.66, "ts": 1770767863, "e": "Position"}, {"uid": "92aa669f-1e40-43df-adbf-29462decf2d8", "bot": false, "x": 93.9, "y": 126.42, "z": -318.74, "ts": 1770767869, "e": "BotKill"}, {"uid": "92aa669f-1e40-43df-adbf-29462decf2d8", "bot": false, "x": 88.25, "y": 126.36, "z": -312.12, "ts": 1770767873, "e": "Position"}, {"uid": "92aa669f-1e40-43df-adbf-29462decf2d8", "bot": false, "x": 84.34, "y": 126.3, "z": -303.54, "ts": 1770767878, "e": "Position"}, {"uid": "92aa669f-1e40-43df-adbf-29462decf2d8", "bot": false, "x": 84.2, "y": 126.26, "z": -302.57, "ts": 1770767880, "e": "Loot"}, {"uid": "92aa669f-1e40-43df-adbf-29462decf2d8", "bot": false, "x": 84.2, "y": 126.26, "z": -302.57, "ts": 1770767880, "e": "Loot"}, {"uid": "92aa669f-1e40-43df-adbf-29462decf2d8", "bot": false, "x": 84.87, "y": 126.33, "z": -297.97, "ts": 1770767883, "e": "Position"}, {"uid": "92aa669f-1e40-43df-adbf-29462decf2d8", "bot": false, "x": 84.08, "y": 128.64, "z": -286.5, "ts": 1770767888, "e": "Position"}, {"uid": "92aa669f-1e40-43df-adbf-29462decf2d8", "bot": false, "x": 103.99, "y": 129.42, "z": -290.99, "ts": 1770767893, "e": "Position"}, {"uid": "92aa669f-1e40-43df-adbf-29462decf2d8", "bot": false, "x": 100.66, "y": 130.99, "z": -282.14, "ts": 1770767898, "e": "Position"}, {"uid": "92aa669f-1e40-43df-adbf-29462decf2d8", "bot": false, "x": 106.07, "y": 130.99, "z": -272.44, "ts": 1770767903, "e": "Position"}, {"uid": "92aa669f-1e40-43df-adbf-29462decf2d8", "bot": false, "x": 112.22, "y": 130.99, "z": -274.6, "ts": 1770767908, "e": "Position"}, {"uid": "92aa669f-1e40-43df-adbf-29462decf2d8", "bot": false, "x": 112.22, "y": 130.99, "z": -274.6, "ts": 1770767908, "e": "BotKill"}, {"uid": "92aa669f-1e40-43df-adbf-29462decf2d8", "bot": false, "x": 113.11, "y": 130.99, "z": -276.74, "ts": 1770767912, "e": "Loot"}, {"uid": "92aa669f-1e40-43df-adbf-29462decf2d8", "bot": false, "x": 113.11, "y": 130.99, "z": -276.74, "ts": 1770767912, "e": "Loot"}, {"uid": "92aa669f-1e40-43df-adbf-29462decf2d8", "bot": false, "x": 113.11, "y": 130.99, "z": -276.74, "ts": 1770767912, "e": "Loot"}, {"uid": "92aa669f-1e40-43df-adbf-29462decf2d8", "bot": false, "x": 112.38, "y": 130.99, "z": -277.89, "ts": 1770767913, "e": "Position"}, {"uid": "92aa669f-1e40-43df-adbf-29462decf2d8", "bot": false, "x": 109.13, "y": 130.99, "z": -277.91, "ts": 1770767918, "e": "Position"}, {"uid": "92aa669f-1e40-43df-adbf-29462decf2d8", "bot": false, "x": 104.68, "y": 130.99, "z": -276.02, "ts": 1770767923, "e": "Position"}, {"uid": "92aa669f-1e40-43df-adbf-29462decf2d8", "bot": false, "x": 110.46, "y": 130.99, "z": -277.83, "ts": 1770767928, "e": "Position"}, {"uid": "92aa669f-1e40-43df-adbf-29462decf2d8", "bot": false, "x": 123.07, "y": 131.08, "z": -274.17, "ts": 1770767933, "e": "Position"}, {"uid": "92aa669f-1e40-43df-adbf-29462decf2d8", "bot": false, "x": 126.59, "y": 129.68, "z": -275.05, "ts": 1770767938, "e": "Position"}, {"uid": "92aa669f-1e40-43df-adbf-29462decf2d8", "bot": false, "x": 116.13, "y": 131.08, "z": -277.91, "ts": 1770767943, "e": "Position"}, {"uid": "92aa669f-1e40-43df-adbf-29462decf2d8", "bot": false, "x": 110.98, "y": 130.99, "z": -275.08, "ts": 1770767948, "e": "Loot"}, {"uid": "92aa669f-1e40-43df-adbf-29462decf2d8", "bot": false, "x": 110.98, "y": 130.99, "z": -275.08, "ts": 1770767948, "e": "Loot"}, {"uid": "92aa669f-1e40-43df-adbf-29462decf2d8", "bot": false, "x": 110.98, "y": 130.99, "z": -275.08, "ts": 1770767948, "e": "Position"}, {"uid": "92aa669f-1e40-43df-adbf-29462decf2d8", "bot": false, "x": 103.41, "y": 130.99, "z": -269.87, "ts": 1770767953, "e": "Position"}, {"uid": "92aa669f-1e40-43df-adbf-29462decf2d8", "bot": false, "x": 102.41, "y": 130.99, "z": -281.94, "ts": 1770767963, "e": "Position"}, {"uid": "92aa669f-1e40-43df-adbf-29462decf2d8", "bot": false, "x": 105.81, "y": 129.8, "z": -289.56, "ts": 1770767973, "e": "Position"}, {"uid": "92aa669f-1e40-43df-adbf-29462decf2d8", "bot": false, "x": 120.3, "y": 129.68, "z": -292.57, "ts": 1770767979, "e": "Position"}, {"uid": "92aa669f-1e40-43df-adbf-29462decf2d8", "bot": false, "x": 131.6, "y": 128.16, "z": -300.82, "ts": 1770767989, "e": "Position"}, {"uid": "92aa669f-1e40-43df-adbf-29462decf2d8", "bot": false, "x": 149.41, "y": 128.54, "z": -306.58, "ts": 1770767994, "e": "Position"}, {"uid": "92aa669f-1e40-43df-adbf-29462decf2d8", "bot": false, "x": 152.72, "y": 128.41, "z": -287.91, "ts": 1770767999, "e": "Position"}, {"uid": "92aa669f-1e40-43df-adbf-29462decf2d8", "bot": false, "x": 161.11, "y": 127.36, "z": -256.45, "ts": 1770768004, "e": "Position"}, {"uid": "92aa669f-1e40-43df-adbf-29462decf2d8", "bot": false, "x": 170.18, "y": 121.8, "z": -225.78, "ts": 1770768009, "e": "Position"}, {"uid": "92aa669f-1e40-43df-adbf-29462decf2d8", "bot": false, "x": 183.02, "y": 116.16, "z": -198.38, "ts": 1770768014, "e": "Position"}, {"uid": "92aa669f-1e40-43df-adbf-29462decf2d8", "bot": false, "x": 194.32, "y": 113.94, "z": -177.77, "ts": 1770768019, "e": "Position"}, {"uid": "92aa669f-1e40-43df-adbf-29462decf2d8", "bot": false, "x": 213.48, "y": 111.65, "z": -151.98, "ts": 1770768024, "e": "Position"}, {"uid": "92aa669f-1e40-43df-adbf-29462decf2d8", "bot": false, "x": 215.94, "y": 112.92, "z": -131.86, "ts": 1770768029, "e": "Position"}, {"uid": "92aa669f-1e40-43df-adbf-29462decf2d8", "bot": false, "x": 217.35, "y": 111.57, "z": -104.0, "ts": 1770768034, "e": "Position"}, {"uid": "92aa669f-1e40-43df-adbf-29462decf2d8", "bot": false, "x": 218.28, "y": 112.35, "z": -81.71, "ts": 1770768039, "e": "Position"}, {"uid": "92aa669f-1e40-43df-adbf-29462decf2d8", "bot": false, "x": 194.74, "y": 114.55, "z": -82.14, "ts": 1770768044, "e": "Position"}, {"uid": "92aa669f-1e40-43df-adbf-29462decf2d8", "bot": false, "x": 189.25, "y": 114.74, "z": -78.48, "ts": 1770768046, "e": "Loot"}, {"uid": "92aa669f-1e40-43df-adbf-29462decf2d8", "bot": false, "x": 189.25, "y": 114.74, "z": -78.48, "ts": 1770768049, "e": "Position"}, {"uid": "92aa669f-1e40-43df-adbf-29462decf2d8", "bot": false, "x": 185.68, "y": 114.45, "z": -81.14, "ts": 1770768054, "e": "Position"}, {"uid": "92aa669f-1e40-43df-adbf-29462decf2d8", "bot": false, "x": 185.68, "y": 114.45, "z": -81.14, "ts": 1770768054, "e": "Loot"}, {"uid": "92aa669f-1e40-43df-adbf-29462decf2d8", "bot": false, "x": 193.16, "y": 114.83, "z": -69.37, "ts": 1770768059, "e": "Position"}]