[{"uid": "f5c3e3de-d49a-4140-ae06-68187d595c69", "bot": false, "x": -233.46, "y": 49.08, "z": 189.89, "ts": 1770806133, "e": "Position"}, {"uid": "f5c3e3de-d49a-4140-ae06-68187d595c69", "bot": false, "x": -213.8, "y": 50.22, "z": 180.22, "ts": 1770806148, "e": "Position"}, {"uid": "f5c3e3de-d49a-4140-ae06-68187d595c69", "bot": false, "x": -188.37, "y": 51.37, "z": 170.47, "ts": 1770806153, "e": "Position"}, {"uid": "f5c3e3de-d49a-4140-ae06-68187d595c69", "bot": false, "x": -183.29, "y": 51.51, "z": 168.45, "ts": 1770806158, "e": "Loot"}, {"uid": "f5c3e3de-d49a-4140-ae06-68187d595c69", "bot": false, "x": -183.29, "y": 51.51, "z": 168.45, "ts": 1770806158, "e": "Position"}, {"uid": "f5c3e3de-d49a-4140-ae06-68187d595c69", "bot": false, "x": -177.39, "y": 51.51, "z": 160.81, "ts": 1770806163, "e": "Position"}, {"uid": "f5c3e3de-d49a-4140-ae06-68187d595c69", "bot": false, "x": -177.39, "y": 51.51, "z": 160.81, "ts": 1770806165, "e": "Loot"}, {"uid": "f5c3e3de-d49a-4140-ae06-68187d595c69", "bot": false, "x": -177.39, "y": 51.51, "z": 160.81, "ts": 1770806165, "e": "Loot"}, {"uid": "f5c3e3de-d49a-4140-ae06-68187d595c69", "bot": false, "x": -178.31, "y": 51.51, "z": 160.46, "ts": 1770806167, "e": "Loot"}, {"uid": "f5c3e3de-d49a-4140-ae06-68187d595c69", "bot": false, "x": -180.86, "y": 51.51, "z": 158.95, "ts": 1770806171, "e": "Loot"}, {"uid": "f5c3e3de-d49a-4140-ae06-68187d595c69", "bot": false, "x": -183.89, "y": 51.33, "z": 162.27, "ts": 1770806173, "e": "Position"}, {"uid": "f5c3e3de-d49a-4140-ae06-68187d595c69", "bot": false, "x": -189.9, "y": 51.33, "z": 172.33, "ts": 1770806178, "e": "Position"}, {"uid": "f5c3e3de-d49a-4140-ae06-68187d595c69", "bot": false, "x": -186.5, "y": 51.37, "z": 166.87, "ts": 1770806182, "e": "Loot"}, {"uid": "f5c3e3de-d49a-4140-ae06-68187d595c69", "bot": false, "x": -185.52, "y": 51.33, "z": 162.35, "ts": 1770806183, "e": "Position"}, {"uid": "f5c3e3de-d49a-4140-ae06-68187d595c69", "bot": false, "x": -173.5, "y": 50.16, "z": 132.05, "ts": 1770806188, "e": "Position"}, {"uid": "f5c3e3de-d49a-4140-ae06-68187d595c69", "bot": false, "x": -158.31, "y": 52.6, "z": 111.62, "ts": 1770806193, "e": "Position"}, {"uid": "f5c3e3de-d49a-4140-ae06-68187d595c69", "bot": false, "x": -148.39, "y": 56.89, "z": 83.87, "ts": 1770806198, "e": "Position"}, {"uid": "f5c3e3de-d49a-4140-ae06-68187d595c69", "bot": false, "x": -138.66, "y": 61.07, "z": 57.83, "ts": 1770806203, "e": "Position"}, {"uid": "f5c3e3de-d49a-4140-ae06-68187d595c69", "bot": false, "x": -136.45, "y": 61.16, "z": 44.32, "ts": 1770806208, "e": "Position"}, {"uid": "f5c3e3de-d49a-4140-ae06-68187d595c69", "bot": false, "x": -135.29, "y": 61.15, "z": 40.97, "ts": 1770806210, "e": "Loot"}, {"uid": "f5c3e3de-d49a-4140-ae06-68187d595c69", "bot": false, "x": -134.63, "y": 61.14, "z": 42.11, "ts": 1770806213, "e": "Position"}, {"uid": "f5c3e3de-d49a-4140-ae06-68187d595c69", "bot": false, "x": -134.63, "y": 61.14, "z": 42.11, "ts": 1770806214, "e": "Loot"}, {"uid": "f5c3e3de-d49a-4140-ae06-68187d595c69", "bot": false, "x": -132.3, "y": 61.14, "z": 36.18, "ts": 1770806218, "e": "Position"}, {"uid": "f5c3e3de-d49a-4140-ae06-68187d595c69", "bot": false, "x": -149.59, "y": 61.03, "z": 36.61, "ts": 1770806223, "e": "Position"}, {"uid": "f5c3e3de-d49a-4140-ae06-68187d595c69", "bot": false, "x": -135.64, "y": 61.18, "z": 56.52, "ts": 1770806228, "e": "Position"}, {"uid": "f5c3e3de-d49a-4140-ae06-68187d595c69", "bot": false, "x": -121.26, "y": 61.16, "z": 65.23, "ts": 1770806233, "e": "Position"}, {"uid": "f5c3e3de-d49a-4140-ae06-68187d595c69", "bot": false, "x": -118.03, "y": 61.09, "z": 65.59, "ts": 1770806235, "e": "Loot"}, {"uid": "f5c3e3de-d49a-4140-ae06-68187d595c69", "bot": false, "x": -119.09, "y": 60.92, "z": 59.06, "ts": 1770806239, "e": "Position"}, {"uid": "f5c3e3de-d49a-4140-ae06-68187d595c69", "bot": false, "x": -125.09, "y": 61.3, "z": 68.96, "ts": 1770806243, "e": "Loot"}, {"uid": "f5c3e3de-d49a-4140-ae06-68187d595c69", "bot": false, "x": -126.24, "y": 61.32, "z": 69.08, "ts": 1770806244, "e": "Position"}, {"uid": "f5c3e3de-d49a-4140-ae06-68187d595c69", "bot": false, "x": -129.73, "y": 61.31, "z": 67.51, "ts": 1770806248, "e": "Loot"}, {"uid": "f5c3e3de-d49a-4140-ae06-68187d595c69", "bot": false, "x": -130.95, "y": 61.31, "z": 67.94, "ts": 1770806249, "e": "Position"}, {"uid": "f5c3e3de-d49a-4140-ae06-68187d595c69", "bot": false, "x": -141.39, "y": 56.47, "z": 86.39, "ts": 1770806254, "e": "Position"}, {"uid": "f5c3e3de-d49a-4140-ae06-68187d595c69", "bot": false, "x": -142.77, "y": 56.29, "z": 88.22, "ts": 1770806254, "e": "BotKill"}, {"uid": "f5c3e3de-d49a-4140-ae06-68187d595c69", "bot": false, "x": -143.22, "y": 56.11, "z": 88.96, "ts": 1770806257, "e": "Loot"}, {"uid": "f5c3e3de-d49a-4140-ae06-68187d595c69", "bot": false, "x": -143.22, "y": 56.11, "z": 88.96, "ts": 1770806258, "e": "Loot"}, {"uid": "f5c3e3de-d49a-4140-ae06-68187d595c69", "bot": false, "x": -151.36, "y": 52.4, "z": 101.31, "ts": 1770806264, "e": "Position"}, {"uid": "f5c3e3de-d49a-4140-ae06-68187d595c69", "bot": false, "x": -148.49, "y": 54.13, "z": 94.71, "ts": 1770806268, "e": "BotKill"}, {"uid": "f5c3e3de-d49a-4140-ae06-68187d595c69", "bot": false, "x": -148.49, "y": 54.13, "z": 94.71, "ts": 1770806268, "e": "BotKill"}, {"uid": "f5c3e3de-d49a-4140-ae06-68187d595c69", "bot": false, "x": -148.49, "y": 54.13, "z": 94.71, "ts": 1770806269, "e": "Position"}, {"uid": "f5c3e3de-d49a-4140-ae06-68187d595c69", "bot": false, "x": -150.07, "y": 53.82, "z": 95.74, "ts": 1770806273, "e": "Loot"}, {"uid": "f5c3e3de-d49a-4140-ae06-68187d595c69", "bot": false, "x": -150.06, "y": 53.84, "z": 95.71, "ts": 1770806274, "e": "Position"}, {"uid": "f5c3e3de-d49a-4140-ae06-68187d595c69", "bot": false, "x": -143.51, "y": 57.29, "z": 85.09, "ts": 1770806279, "e": "Position"}, {"uid": "f5c3e3de-d49a-4140-ae06-68187d595c69", "bot": false, "x": -145.93, "y": 56.69, "z": 86.09, "ts": 1770806289, "e": "Position"}, {"uid": "f5c3e3de-d49a-4140-ae06-68187d595c69", "bot": false, "x": -156.41, "y": 52.42, "z": 107.89, "ts": 1770806294, "e": "Position"}, {"uid": "f5c3e3de-d49a-4140-ae06-68187d595c69", "bot": false, "x": -174.02, "y": 50.17, "z": 130.47, "ts": 1770806299, "e": "Position"}, {"uid": "f5c3e3de-d49a-4140-ae06-68187d595c69", "bot": false, "x": -184.29, "y": 51.27, "z": 143.44, "ts": 1770806304, "e": "Position"}, {"uid": "f5c3e3de-d49a-4140-ae06-68187d595c69", "bot": false, "x": -184.24, "y": 51.21, "z": 146.04, "ts": 1770806309, "e": "Position"}, {"uid": "f5c3e3de-d49a-4140-ae06-68187d595c69", "bot": false, "x": -168.45, "y": 50.32, "z": 128.11, "ts": 1770806314, "e": "Position"}, {"uid": "f5c3e3de-d49a-4140-ae06-68187d595c69", "bot": false, "x": -146.37, "y": 50.72, "z": 121.89, "ts": 1770806319, "e": "Position"}, {"uid": "f5c3e3de-d49a-4140-ae06-68187d595c69", "bot": false, "x": -120.4, "y": 50.3, "z": 132.64, "ts": 1770806324, "e": "Position"}, {"uid": "f5c3e3de-d49a-4140-ae06-68187d595c69", "bot": false, "x": -92.28, "y": 51.05, "z": 126.74, "ts": 1770806329, "e": "Position"}, {"uid": "f5c3e3de-d49a-4140-ae06-68187d595c69", "bot": false, "x": -69.31, "y": 49.9, "z": 125.61, "ts": 1770806334, "e": "Position"}, {"uid": "f5c3e3de-d49a-4140-ae06-68187d595c69", "bot": false, "x": -70.91, "y": 52.04, "z": 120.28, "ts": 1770806339, "e": "Position"}, {"uid": "f5c3e3de-d49a-4140-ae06-68187d595c69", "bot": false, "x": -47.59, "y": 46.21, "z": 115.57, "ts": 1770806344, "e": "Position"}, {"uid": "f5c3e3de-d49a-4140-ae06-68187d595c69", "bot": false, "x": -16.77, "y": 43.24, "z": 108.63, "ts": 1770806349, "e": "Position"}, {"uid": "f5c3e3de-d49a-4140-ae06-68187d595c69", "bot": false, "x": 1.19, "y": 43.93, "z": 91.28, "ts": 1770806354, "e": "Position"}, {"uid": "f5c3e3de-d49a-4140-ae06-68187d595c69", "bot": false, "x": 10.16, "y": 43.77, "z": 67.91, "ts": 1770806359, "e": "Position"}, {"uid": "f5c3e3de-d49a-4140-ae06-68187d595c69", "bot": false, "x": 10.71, "y": 43.77, "z": 55.98, "ts": 1770806364, "e": "Position"}, {"uid": "f5c3e3de-d49a-4140-ae06-68187d595c69", "bot": false, "x": 7.79, "y": 43.77, "z": 55.02, "ts": 1770806369, "e": "Position"}, {"uid": "f5c3e3de-d49a-4140-ae06-68187d595c69", "bot": false, "x": -6.3, "y": 43.72, "z": 50.02, "ts": 1770806374, "e": "Position"}, {"uid": "f5c3e3de-d49a-4140-ae06-68187d595c69", "bot": false, "x": -4.48, "y": 43.77, "z": 41.34, "ts": 1770806379, "e": "Position"}, {"uid": "f5c3e3de-d49a-4140-ae06-68187d595c69", "bot": false, "x": 2.0, "y": 43.77, "z": 65.75, "ts": 1770806384, "e": "Position"}, {"uid": "f5c3e3de-d49a-4140-ae06-68187d595c69", "bot": false, "x": 27.59, "y": 43.69, "z": 65.74, "ts": 1770806389, "e": "Position"}, {"uid": "f5c3e3de-d49a-4140-ae06-68187d595c69", "bot": false, "x": 31.13, "y": 43.76, "z": 65.56, "ts": 1770806394, "e": "Position"}, {"uid": "f5c3e3de-d49a-4140-ae06-68187d595c69", "bot": false, "x": 48.94, "y": 43.94, "z": 74.22, "ts": 1770806399, "e": "Position"}, {"uid": "f5c3e3de-d49a-4140-ae06-68187d595c69", "bot": false, "x": 65.05, "y": 43.89, "z": 96.35, "ts": 1770806404, "e": "Position"}, {"uid": "f5c3e3de-d49a-4140-ae06-68187d595c69", "bot": false, "x": 89.68, "y": 42.13, "z": 112.24, "ts": 1770806409, "e": "Position"}, {"uid": "f5c3e3de-d49a-4140-ae06-68187d595c69", "bot": false, "x": 97.93, "y": 42.32, "z": 141.02, "ts": 1770806415, "e": "Position"}, {"uid": "f5c3e3de-d49a-4140-ae06-68187d595c69", "bot": false, "x": 82.42, "y": 42.23, "z": 156.52, "ts": 1770806420, "e": "Position"}, {"uid": "f5c3e3de-d49a-4140-ae06-68187d595c69", "bot": false, "x": 59.24, "y": 46.08, "z": 167.74, "ts": 1770806425, "e": "Position"}, {"uid": "f5c3e3de-d49a-4140-ae06-68187d595c69", "bot": false, "x": 34.18, "y": 47.1, "z": 164.02, "ts": 1770806430, "e": "Position"}, {"uid": "f5c3e3de-d49a-4140-ae06-68187d595c69", "bot": false, "x": 17.04, "y": 47.1, "z": 163.69, "ts": 1770806435, "e": "Position"}, {"uid": "f5c3e3de-d49a-4140-ae06-68187d595c69", "bot": false, "x": 14.04, "y": 46.59, "z": 173.25, "ts": 1770806454, "e": "BotKill"}, {"uid": "f5c3e3de-d49a-4140-ae06-68187d595c69", "bot": false, "x": 14.16, "y": 45.8, "z": 174.63, "ts": 1770806455, "e": "Position"}, {"uid": "f5c3e3de-d49a-4140-ae06-68187d595c69", "bot": false, "x": 16.31, "y": 42.9, "z": 193.34, "ts": 1770806460, "e": "Loot"}, {"uid": "f5c3e3de-d49a-4140-ae06-68187d595c69", "bot": false, "x": 16.39, "y": 42.9, "z": 193.18, "ts": 1770806460, "e": "Position"}, {"uid": "f5c3e3de-d49a-4140-ae06-68187d595c69", "bot": false, "x": 15.24, "y": 45.8, "z": 205.05, "ts": 1770806465, "e": "Position"}, {"uid": "f5c3e3de-d49a-4140-ae06-68187d595c69", "bot": false, "x": 8.51, "y": 38.4, "z": 199.4, "ts": 1770806470, "e": "Position"}, {"uid": "f5c3e3de-d49a-4140-ae06-68187d595c69", "bot": false, "x": 11.97, "y": 34.24, "z": 224.99, "ts": 1770806475, "e": "Position"}, {"uid": "f5c3e3de-d49a-4140-ae06-68187d595c69", "bot": false, "x": 26.38, "y": 34.24, "z": 234.02, "ts": 1770806480, "e": "Position"}, {"uid": "f5c3e3de-d49a-4140-ae06-68187d595c69", "bot": false, "x": 40.3, "y": 34.24, "z": 234.6, "ts": 1770806485, "e": "Position"}, {"uid": "f5c3e3de-d49a-4140-ae06-68187d595c69", "bot": false, "x": 44.73, "y": 34.22, "z": 244.11, "ts": 1770806515, "e": "Position"}, {"uid": "f5c3e3de-d49a-4140-ae06-68187d595c69", "bot": false, "x": 37.54, "y": 34.11, "z": 249.55, "ts": 1770806520, "e": "Position"}, {"uid": "f5c3e3de-d49a-4140-ae06-68187d595c69", "bot": false, "x": 66.04, "y": 34.17, "z": 256.09, "ts": 1770806525, "e": "Position"}, {"uid": "f5c3e3de-d49a-4140-ae06-68187d595c69", "bot": false, "x": 95.08, "y": 34.19, "z": 263.32, "ts": 1770806530, "e": "Position"}, {"uid": "f5c3e3de-d49a-4140-ae06-68187d595c69", "bot": false, "x": 116.01, "y": 34.26, "z": 242.73, "ts": 1770806535, "e": "Position"}, {"uid": "f5c3e3de-d49a-4140-ae06-68187d595c69", "bot": false, "x": 128.78, "y": 34.4, "z": 219.92, "ts": 1770806540, "e": "Position"}, {"uid": "f5c3e3de-d49a-4140-ae06-68187d595c69", "bot": false, "x": 128.49, "y": 35.13, "z": 199.45, "ts": 1770806545, "e": "Position"}, {"uid": "f5c3e3de-d49a-4140-ae06-68187d595c69", "bot": false, "x": 135.18, "y": 42.15, "z": 175.3, "ts": 1770806550, "e": "Position"}, {"uid": "f5c3e3de-d49a-4140-ae06-68187d595c69", "bot": false, "x": 152.56, "y": 38.56, "z": 168.55, "ts": 1770806555, "e": "Position"}, {"uid": "f5c3e3de-d49a-4140-ae06-68187d595c69", "bot": false, "x": 160.31, "y": 44.16, "z": 146.5, "ts": 1770806560, "e": "Position"}, {"uid": "f5c3e3de-d49a-4140-ae06-68187d595c69", "bot": false, "x": 143.23, "y": 43.09, "z": 122.87, "ts": 1770806565, "e": "Position"}, {"uid": "f5c3e3de-d49a-4140-ae06-68187d595c69", "bot": false, "x": 139.99, "y": 37.97, "z": 96.58, "ts": 1770806570, "e": "Position"}, {"uid": "f5c3e3de-d49a-4140-ae06-68187d595c69", "bot": false, "x": 145.56, "y": 38.94, "z": 80.11, "ts": 1770806575, "e": "Position"}, {"uid": "f5c3e3de-d49a-4140-ae06-68187d595c69", "bot": false, "x": 145.05, "y": 35.65, "z": 58.95, "ts": 1770806580, "e": "Position"}, {"uid": "f5c3e3de-d49a-4140-ae06-68187d595c69", "bot": false, "x": 153.02, "y": 33.42, "z": 42.19, "ts": 1770806585, "e": "Position"}, {"uid": "f5c3e3de-d49a-4140-ae06-68187d595c69", "bot": false, "x": 158.96, "y": 33.07, "z": 33.52, "ts": 1770806590, "e": "Position"}, {"uid": "f5c3e3de-d49a-4140-ae06-68187d595c69", "bot": false, "x": 159.7, "y": 33.03, "z": 27.67, "ts": 1770806611, "e": "Position"}, {"uid": "f5c3e3de-d49a-4140-ae06-68187d595c69", "bot": false, "x": 158.71, "y": 33.13, "z": 23.63, "ts": 1770806616, "e": "Position"}, {"uid": "f5c3e3de-d49a-4140-ae06-68187d595c69", "bot": false, "x": 160.15, "y": 33.03, "z": 31.78, "ts": 1770806626, "e": "Position"}, {"uid": "f5c3e3de-d49a-4140-ae06-68187d595c69", "bot": false, "x": 158.62, "y": 33.06, "z": 25.62, "ts": 1770806636, "e": "Position"}, {"uid": "f5c3e3de-d49a-4140-ae06-68187d595c69", "bot": false, "x": 153.16, "y": 33.23, "z": 17.62, "ts": 1770806641, "e": "Position"}, {"uid": "f5c3e3de-d49a-4140-ae06-68187d595c69", "bot": false, "x": 150.76, "y": 33.36, "z": 13.59, "ts": 1770806646, "e": "Position"}, {"uid": "f5c3e3de-d49a-4140-ae06-68187d595c69", "bot": false, "x": 130.51, "y": 33.97, "z": 4.78, "ts": 1770806651, "e": "Position"}, {"uid": "f5c3e3de-d49a-4140-ae06-68187d595c69", "bot": false, "x": 128.29, "y": 33.83, "z": -1.49, "ts": 1770806656, "e": "Position"}, {"uid": "f5c3e3de-d49a-4140-ae06-68187d595c69", "bot": false, "x": 152.93, "y": 33.76, "z": 6.77, "ts": 1770806661, "e": "Position"}, {"uid": "f5c3e3de-d49a-4140-ae06-68187d595c69", "bot": false, "x": 158.66, "y": 33.83, "z": 9.09, "ts": 1770806666, "e": "Position"}, {"uid": "f5c3e3de-d49a-4140-ae06-68187d595c69", "bot": false, "x": 144.24, "y": 33.75, "z": 1.63, "ts": 1770806676, "e": "Position"}, {"uid": "f5c3e3de-d49a-4140-ae06-68187d595c69", "bot": false, "x": 136.82, "y": 33.86, "z": -0.26, "ts": 1770806681, "e": "Position"}, {"uid": "f5c3e3de-d49a-4140-ae06-68187d595c69", "bot": false, "x": 128.62, "y": 33.92, "z": -3.48, "ts": 1770806686, "e": "Position"}, {"uid": "f5c3e3de-d49a-4140-ae06-68187d595c69", "bot": false, "x": 119.06, "y": 33.94, "z": -3.79, "ts": 1770806691, "e": "Position"}, {"uid": "f5c3e3de-d49a-4140-ae06-68187d595c69", "bot": false, "x": 109.79, "y": 33.94, "z": -2.53, "ts": 1770806696, "e": "Position"}, {"uid": "f5c3e3de-d49a-4140-ae06-68187d595c69", "bot": false, "x": 110.98, "y": 34.04, "z": 8.0, "ts": 1770806701, "e": "Position"}, {"uid": "f5c3e3de-d49a-4140-ae06-68187d595c69", "bot": false, "x": 112.25, "y": 34.08, "z": 23.77, "ts": 1770806706, "e": "Position"}, {"uid": "f5c3e3de-d49a-4140-ae06-68187d595c69", "bot": false, "x": 100.96, "y": 35.55, "z": 34.09, "ts": 1770806716, "e": "Position"}, {"uid": "f5c3e3de-d49a-4140-ae06-68187d595c69", "bot": false, "x": 93.11, "y": 37.51, "z": 41.2, "ts": 1770806721, "e": "Position"}, {"uid": "f5c3e3de-d49a-4140-ae06-68187d595c69", "bot": false, "x": 88.07, "y": 38.3, "z": 39.78, "ts": 1770806726, "e": "Position"}, {"uid": "f5c3e3de-d49a-4140-ae06-68187d595c69", "bot": false, "x": 79.49, "y": 40.82, "z": 46.69, "ts": 1770806731, "e": "Position"}, {"uid": "f5c3e3de-d49a-4140-ae06-68187d595c69", "bot": false, "x": 66.42, "y": 43.62, "z": 57.67, "ts": 1770806741, "e": "Position"}, {"uid": "f5c3e3de-d49a-4140-ae06-68187d595c69", "bot": false, "x": 60.68, "y": 43.97, "z": 64.9, "ts": 1770806746, "e": "Position"}, {"uid": "f5c3e3de-d49a-4140-ae06-68187d595c69", "bot": false, "x": 51.91, "y": 43.87, "z": 71.5, "ts": 1770806751, "e": "Position"}, {"uid": "f5c3e3de-d49a-4140-ae06-68187d595c69", "bot": false, "x": 53.3, "y": 44.1, "z": 69.09, "ts": 1770806756, "e": "Position"}, {"uid": "f5c3e3de-d49a-4140-ae06-68187d595c69", "bot": false, "x": 39.58, "y": 43.92, "z": 65.76, "ts": 1770806761, "e": "Position"}, {"uid": "f5c3e3de-d49a-4140-ae06-68187d595c69", "bot": false, "x": 34.41, "y": 43.81, "z": 63.88, "ts": 1770806766, "e": "Position"}, {"uid": "f5c3e3de-d49a-4140-ae06-68187d595c69", "bot": false, "x": 31.6, "y": 43.67, "z": 62.64, "ts": 1770806771, "e": "Loot"}, {"uid": "f5c3e3de-d49a-4140-ae06-68187d595c69", "bot": false, "x": 32.02, "y": 43.72, "z": 59.25, "ts": 1770806777, "e": "Position"}, {"uid": "f5c3e3de-d49a-4140-ae06-68187d595c69", "bot": false, "x": 41.89, "y": 43.89, "z": 64.45, "ts": 1770806782, "e": "Position"}, {"uid": "f5c3e3de-d49a-4140-ae06-68187d595c69", "bot": false, "x": 59.93, "y": 44.03, "z": 71.6, "ts": 1770806787, "e": "Position"}, {"uid": "f5c3e3de-d49a-4140-ae06-68187d595c69", "bot": false, "x": 56.13, "y": 43.79, "z": 61.18, "ts": 1770806792, "e": "Position"}, {"uid": "f5c3e3de-d49a-4140-ae06-68187d595c69", "bot": false, "x": 53.14, "y": 42.91, "z": 38.4, "ts": 1770806797, "e": "Position"}, {"uid": "f5c3e3de-d49a-4140-ae06-68187d595c69", "bot": false, "x": 58.66, "y": 43.68, "z": 57.78, "ts": 1770806802, "e": "Position"}, {"uid": "f5c3e3de-d49a-4140-ae06-68187d595c69", "bot": false, "x": 46.29, "y": 43.92, "z": 81.37, "ts": 1770806807, "e": "Position"}, {"uid": "f5c3e3de-d49a-4140-ae06-68187d595c69", "bot": false, "x": 21.12, "y": 43.95, "z": 94.35, "ts": 1770806812, "e": "Position"}, {"uid": "f5c3e3de-d49a-4140-ae06-68187d595c69", "bot": false, "x": -2.92, "y": 43.72, "z": 104.93, "ts": 1770806817, "e": "Position"}, {"uid": "f5c3e3de-d49a-4140-ae06-68187d595c69", "bot": false, "x": -21.37, "y": 43.75, "z": 110.33, "ts": 1770806822, "e": "Position"}, {"uid": "f5c3e3de-d49a-4140-ae06-68187d595c69", "bot": false, "x": -46.75, "y": 46.13, "z": 115.7, "ts": 1770806827, "e": "Position"}, {"uid": "f5c3e3de-d49a-4140-ae06-68187d595c69", "bot": false, "x": -67.06, "y": 50.18, "z": 122.33, "ts": 1770806832, "e": "Position"}, {"uid": "f5c3e3de-d49a-4140-ae06-68187d595c69", "bot": false, "x": -85.69, "y": 51.34, "z": 117.2, "ts": 1770806837, "e": "Position"}, {"uid": "f5c3e3de-d49a-4140-ae06-68187d595c69", "bot": false, "x": -104.14, "y": 49.68, "z": 129.06, "ts": 1770806842, "e": "Position"}, {"uid": "f5c3e3de-d49a-4140-ae06-68187d595c69", "bot": false, "x": -121.89, "y": 50.37, "z": 133.1, "ts": 1770806847, "e": "Position"}, {"uid": "f5c3e3de-d49a-4140-ae06-68187d595c69", "bot": false, "x": -144.92, "y": 50.54, "z": 125.65, "ts": 1770806852, "e": "Position"}, {"uid": "f5c3e3de-d49a-4140-ae06-68187d595c69", "bot": false, "x": -149.65, "y": 51.57, "z": 110.46, "ts": 1770806857, "e": "Position"}, {"uid": "f5c3e3de-d49a-4140-ae06-68187d595c69", "bot": false, "x": -153.54, "y": 53.47, "z": 95.87, "ts": 1770806862, "e": "Position"}, {"uid": "f5c3e3de-d49a-4140-ae06-68187d595c69", "bot": false, "x": -175.64, "y": 51.51, "z": 99.55, "ts": 1770806867, "e": "Position"}, {"uid": "f5c3e3de-d49a-4140-ae06-68187d595c69", "bot": false, "x": -194.59, "y": 54.55, "z": 92.9, "ts": 1770806872, "e": "Position"}, {"uid": "f5c3e3de-d49a-4140-ae06-68187d595c69", "bot": false, "x": -218.35, "y": 53.12, "z": 93.34, "ts": 1770806877, "e": "Position"}, {"uid": "f5c3e3de-d49a-4140-ae06-68187d595c69", "bot": false, "x": -245.78, "y": 50.97, "z": 95.62, "ts": 1770806882, "e": "Position"}, {"uid": "f5c3e3de-d49a-4140-ae06-68187d595c69", "bot": false, "x": -270.49, "y": 40.69, "z": 87.2, "ts": 1770806887, "e": "Position"}, {"uid": "f5c3e3de-d49a-4140-ae06-68187d595c69", "bot": false, "x": -276.92, "y": 40.53, "z": 77.74, "ts": 1770806892, "e": "Position"}, {"uid": "f5c3e3de-d49a-4140-ae06-68187d595c69", "bot": false, "x": -275.79, "y": 40.46, "z": 73.61, "ts": 1770806902, "e": "Position"}, {"uid": "f5c3e3de-d49a-4140-ae06-68187d595c69", "bot": false, "x": -298.84, "y": 40.64, "z": 67.96, "ts": 1770806907, "e": "Position"}, {"uid": "f5c3e3de-d49a-4140-ae06-68187d595c69", "bot": false, "x": -312.32, "y": 40.6, "z": 51.49, "ts": 1770806912, "e": "Position"}, {"uid": "f5c3e3de-d49a-4140-ae06-68187d595c69", "bot": false, "x": -322.05, "y": 39.57, "z": 35.61, "ts": 1770806917, "e": "Position"}, {"uid": "f5c3e3de-d49a-4140-ae06-68187d595c69", "bot": false, "x": -322.51, "y": 39.58, "z": 35.12, "ts": 1770806917, "e": "BotKill"}, {"uid": "f5c3e3de-d49a-4140-ae06-68187d595c69", "bot": false, "x": -332.06, "y": 40.1, "z": 25.42, "ts": 1770806922, "e": "Position"}, {"uid": "f5c3e3de-d49a-4140-ae06-68187d595c69", "bot": false, "x": -332.06, "y": 40.1, "z": 25.42, "ts": 1770806923, "e": "Loot"}, {"uid": "f5c3e3de-d49a-4140-ae06-68187d595c69", "bot": false, "x": -341.74, "y": 39.51, "z": 12.37, "ts": 1770806927, "e": "Position"}, {"uid": "f5c3e3de-d49a-4140-ae06-68187d595c69", "bot": false, "x": -355.84, "y": 39.72, "z": -3.58, "ts": 1770806932, "e": "Position"}, {"uid": "f5c3e3de-d49a-4140-ae06-68187d595c69", "bot": false, "x": -371.38, "y": 41.56, "z": -21.95, "ts": 1770806937, "e": "Position"}, {"uid": "f5c3e3de-d49a-4140-ae06-68187d595c69", "bot": false, "x": -371.38, "y": 41.56, "z": -21.95, "ts": 1770806938, "e": "Loot"}]