[{"uid": "748892a8-0d0e-40ab-8b16-a34c6d5c413d", "bot": false, "x": 211.06, "y": 38.98, "z": 216.32, "ts": 1770977165, "e": "Position"}, {"uid": "748892a8-0d0e-40ab-8b16-a34c6d5c413d", "bot": false, "x": 215.13, "y": 36.98, "z": 210.93, "ts": 1770977180, "e": "Position"}, {"uid": "748892a8-0d0e-40ab-8b16-a34c6d5c413d", "bot": false, "x": 222.49, "y": 37.79, "z": 199.89, "ts": 1770977185, "e": "Position"}, {"uid": "748892a8-0d0e-40ab-8b16-a34c6d5c413d", "bot": false, "x": 236.71, "y": 37.45, "z": 203.52, "ts": 1770977190, "e": "Loot"}, {"uid": "748892a8-0d0e-40ab-8b16-a34c6d5c413d", "bot": false, "x": 237.03, "y": 37.45, "z": 203.49, "ts": 1770977190, "e": "Position"}, {"uid": "748892a8-0d0e-40ab-8b16-a34c6d5c413d", "bot": false, "x": 241.92, "y": 37.45, "z": 201.8, "ts": 1770977195, "e": "Position"}, {"uid": "748892a8-0d0e-40ab-8b16-a34c6d5c413d", "bot": false, "x": 241.92, "y": 37.45, "z": 201.8, "ts": 1770977197, "e": "Loot"}, {"uid": "748892a8-0d0e-40ab-8b16-a34c6d5c413d", "bot": false, "x": 246.89, "y": 36.75, "z": 190.33, "ts": 1770977200, "e": "Position"}, {"uid": "748892a8-0d0e-40ab-8b16-a34c6d5c413d", "bot": false, "x": 244.32, "y": 36.68, "z": 186.0, "ts": 1770977205, "e": "Position"}, {"uid": "748892a8-0d0e-40ab-8b16-a34c6d5c413d", "bot": false, "x": 246.32, "y": 38.2, "z": 181.14, "ts": 1770977210, "e": "Position"}, {"uid": "748892a8-0d0e-40ab-8b16-a34c6d5c413d", "bot": false, "x": 241.92, "y": 36.64, "z": 185.32, "ts": 1770977215, "e": "Position"}, {"uid": "748892a8-0d0e-40ab-8b16-a34c6d5c413d", "bot": false, "x": 227.55, "y": 36.59, "z": 182.21, "ts": 1770977225, "e": "Position"}, {"uid": "748892a8-0d0e-40ab-8b16-a34c6d5c413d", "bot": false, "x": 219.01, "y": 37.0, "z": 183.96, "ts": 1770977230, "e": "Position"}, {"uid": "748892a8-0d0e-40ab-8b16-a34c6d5c413d", "bot": false, "x": 225.44, "y": 37.03, "z": 188.22, "ts": 1770977236, "e": "Position"}, {"uid": "748892a8-0d0e-40ab-8b16-a34c6d5c413d", "bot": false, "x": 226.01, "y": 36.67, "z": 184.92, "ts": 1770977241, "e": "Position"}, {"uid": "748892a8-0d0e-40ab-8b16-a34c6d5c413d", "bot": false, "x": 229.71, "y": 36.64, "z": 187.09, "ts": 1770977246, "e": "Position"}, {"uid": "748892a8-0d0e-40ab-8b16-a34c6d5c413d", "bot": false, "x": 228.96, "y": 36.59, "z": 184.4, "ts": 1770977250, "e": "BotKill"}, {"uid": "748892a8-0d0e-40ab-8b16-a34c6d5c413d", "bot": false, "x": 229.53, "y": 36.58, "z": 184.79, "ts": 1770977251, "e": "Position"}, {"uid": "748892a8-0d0e-40ab-8b16-a34c6d5c413d", "bot": false, "x": 228.72, "y": 36.62, "z": 185.55, "ts": 1770977252, "e": "Loot"}, {"uid": "748892a8-0d0e-40ab-8b16-a34c6d5c413d", "bot": false, "x": 228.72, "y": 36.62, "z": 185.55, "ts": 1770977252, "e": "Loot"}, {"uid": "748892a8-0d0e-40ab-8b16-a34c6d5c413d", "bot": false, "x": 220.53, "y": 36.58, "z": 175.91, "ts": 1770977256, "e": "Position"}, {"uid": "748892a8-0d0e-40ab-8b16-a34c6d5c413d", "bot": false, "x": 219.69, "y": 36.61, "z": 174.75, "ts": 1770977258, "e": "Loot"}, {"uid": "748892a8-0d0e-40ab-8b16-a34c6d5c413d", "bot": false, "x": 225.04, "y": 36.58, "z": 177.01, "ts": 1770977261, "e": "Position"}, {"uid": "748892a8-0d0e-40ab-8b16-a34c6d5c413d", "bot": false, "x": 238.39, "y": 36.61, "z": 186.83, "ts": 1770977266, "e": "Position"}, {"uid": "748892a8-0d0e-40ab-8b16-a34c6d5c413d", "bot": false, "x": 238.39, "y": 36.61, "z": 186.83, "ts": 1770977266, "e": "Loot"}, {"uid": "748892a8-0d0e-40ab-8b16-a34c6d5c413d", "bot": false, "x": 217.24, "y": 37.05, "z": 182.68, "ts": 1770977271, "e": "Position"}, {"uid": "748892a8-0d0e-40ab-8b16-a34c6d5c413d", "bot": false, "x": 203.28, "y": 37.78, "z": 190.6, "ts": 1770977276, "e": "Position"}, {"uid": "748892a8-0d0e-40ab-8b16-a34c6d5c413d", "bot": false, "x": 176.99, "y": 39.21, "z": 177.92, "ts": 1770977281, "e": "Position"}, {"uid": "748892a8-0d0e-40ab-8b16-a34c6d5c413d", "bot": false, "x": 171.8, "y": 39.55, "z": 157.22, "ts": 1770977286, "e": "Position"}, {"uid": "748892a8-0d0e-40ab-8b16-a34c6d5c413d", "bot": false, "x": 182.48, "y": 37.58, "z": 145.59, "ts": 1770977291, "e": "Position"}, {"uid": "748892a8-0d0e-40ab-8b16-a34c6d5c413d", "bot": false, "x": 194.5, "y": 36.57, "z": 119.91, "ts": 1770977296, "e": "Position"}, {"uid": "748892a8-0d0e-40ab-8b16-a34c6d5c413d", "bot": false, "x": 208.75, "y": 37.03, "z": 102.93, "ts": 1770977301, "e": "Position"}, {"uid": "748892a8-0d0e-40ab-8b16-a34c6d5c413d", "bot": false, "x": 220.84, "y": 41.59, "z": 89.45, "ts": 1770977306, "e": "Position"}, {"uid": "748892a8-0d0e-40ab-8b16-a34c6d5c413d", "bot": false, "x": 222.86, "y": 42.26, "z": 82.02, "ts": 1770977311, "e": "Loot"}, {"uid": "748892a8-0d0e-40ab-8b16-a34c6d5c413d", "bot": false, "x": 223.36, "y": 42.26, "z": 81.94, "ts": 1770977311, "e": "Position"}, {"uid": "748892a8-0d0e-40ab-8b16-a34c6d5c413d", "bot": false, "x": 229.89, "y": 42.26, "z": 74.36, "ts": 1770977316, "e": "Position"}, {"uid": "748892a8-0d0e-40ab-8b16-a34c6d5c413d", "bot": false, "x": 231.32, "y": 42.35, "z": 68.66, "ts": 1770977321, "e": "Position"}, {"uid": "748892a8-0d0e-40ab-8b16-a34c6d5c413d", "bot": false, "x": 241.19, "y": 43.32, "z": 48.24, "ts": 1770977326, "e": "Position"}, {"uid": "748892a8-0d0e-40ab-8b16-a34c6d5c413d", "bot": false, "x": 247.83, "y": 43.52, "z": 33.38, "ts": 1770977331, "e": "Position"}, {"uid": "748892a8-0d0e-40ab-8b16-a34c6d5c413d", "bot": false, "x": 248.97, "y": 43.51, "z": 21.39, "ts": 1770977336, "e": "Position"}, {"uid": "748892a8-0d0e-40ab-8b16-a34c6d5c413d", "bot": false, "x": 248.97, "y": 43.51, "z": 21.39, "ts": 1770977337, "e": "Loot"}, {"uid": "748892a8-0d0e-40ab-8b16-a34c6d5c413d", "bot": false, "x": 256.8, "y": 43.51, "z": 27.52, "ts": 1770977346, "e": "Position"}, {"uid": "748892a8-0d0e-40ab-8b16-a34c6d5c413d", "bot": false, "x": 256.65, "y": 43.51, "z": 27.87, "ts": 1770977349, "e": "Loot"}, {"uid": "748892a8-0d0e-40ab-8b16-a34c6d5c413d", "bot": false, "x": 258.43, "y": 44.5, "z": 32.31, "ts": 1770977351, "e": "Position"}, {"uid": "748892a8-0d0e-40ab-8b16-a34c6d5c413d", "bot": false, "x": 256.09, "y": 48.58, "z": 22.15, "ts": 1770977356, "e": "Position"}, {"uid": "748892a8-0d0e-40ab-8b16-a34c6d5c413d", "bot": false, "x": 253.77, "y": 48.58, "z": 31.3, "ts": 1770977361, "e": "Position"}, {"uid": "748892a8-0d0e-40ab-8b16-a34c6d5c413d", "bot": false, "x": 253.65, "y": 48.58, "z": 30.93, "ts": 1770977362, "e": "Loot"}, {"uid": "748892a8-0d0e-40ab-8b16-a34c6d5c413d", "bot": false, "x": 254.27, "y": 48.58, "z": 28.25, "ts": 1770977366, "e": "Position"}, {"uid": "748892a8-0d0e-40ab-8b16-a34c6d5c413d", "bot": false, "x": 246.24, "y": 49.4, "z": 29.08, "ts": 1770977371, "e": "Position"}, {"uid": "748892a8-0d0e-40ab-8b16-a34c6d5c413d", "bot": false, "x": 248.32, "y": 48.59, "z": 39.9, "ts": 1770977376, "e": "Loot"}, {"uid": "748892a8-0d0e-40ab-8b16-a34c6d5c413d", "bot": false, "x": 248.32, "y": 48.59, "z": 39.9, "ts": 1770977376, "e": "Position"}, {"uid": "748892a8-0d0e-40ab-8b16-a34c6d5c413d", "bot": false, "x": 241.08, "y": 43.3, "z": 42.76, "ts": 1770977381, "e": "Position"}, {"uid": "748892a8-0d0e-40ab-8b16-a34c6d5c413d", "bot": false, "x": 227.87, "y": 43.34, "z": 37.18, "ts": 1770977386, "e": "Position"}, {"uid": "748892a8-0d0e-40ab-8b16-a34c6d5c413d", "bot": false, "x": 218.23, "y": 43.29, "z": 36.94, "ts": 1770977391, "e": "Position"}, {"uid": "748892a8-0d0e-40ab-8b16-a34c6d5c413d", "bot": false, "x": 216.64, "y": 43.29, "z": 40.32, "ts": 1770977396, "e": "Position"}, {"uid": "748892a8-0d0e-40ab-8b16-a34c6d5c413d", "bot": false, "x": 211.13, "y": 43.6, "z": 50.04, "ts": 1770977401, "e": "Position"}, {"uid": "748892a8-0d0e-40ab-8b16-a34c6d5c413d", "bot": false, "x": 209.97, "y": 43.6, "z": 48.91, "ts": 1770977404, "e": "Loot"}, {"uid": "748892a8-0d0e-40ab-8b16-a34c6d5c413d", "bot": false, "x": 203.84, "y": 43.42, "z": 52.98, "ts": 1770977406, "e": "Position"}, {"uid": "748892a8-0d0e-40ab-8b16-a34c6d5c413d", "bot": false, "x": 205.05, "y": 42.9, "z": 62.91, "ts": 1770977412, "e": "Position"}, {"uid": "748892a8-0d0e-40ab-8b16-a34c6d5c413d", "bot": false, "x": 218.07, "y": 43.39, "z": 57.22, "ts": 1770977416, "e": "BotKilled"}, {"uid": "748892a8-0d0e-40ab-8b16-a34c6d5c413d", "bot": false, "x": 218.01, "y": 43.36, "z": 57.35, "ts": 1770977417, "e": "Position"}]