[{"uid": "81d929b0-7372-44f6-a8f7-a5c832e9aa7f", "bot": false, "x": 210.38, "y": 39.12, "z": 216.17, "ts": 1770709375, "e": "Position"}, {"uid": "81d929b0-7372-44f6-a8f7-a5c832e9aa7f", "bot": false, "x": 211.88, "y": 37.78, "z": 190.37, "ts": 1770709395, "e": "Position"}, {"uid": "81d929b0-7372-44f6-a8f7-a5c832e9aa7f", "bot": false, "x": 224.87, "y": 36.69, "z": 184.6, "ts": 1770709400, "e": "Position"}, {"uid": "81d929b0-7372-44f6-a8f7-a5c832e9aa7f", "bot": false, "x": 224.87, "y": 36.69, "z": 184.6, "ts": 1770709401, "e": "Loot"}, {"uid": "81d929b0-7372-44f6-a8f7-a5c832e9aa7f", "bot": false, "x": 219.25, "y": 36.67, "z": 175.97, "ts": 1770709405, "e": "Position"}, {"uid": "81d929b0-7372-44f6-a8f7-a5c832e9aa7f", "bot": false, "x": 219.25, "y": 36.67, "z": 175.97, "ts": 1770709406, "e": "Loot"}, {"uid": "81d929b0-7372-44f6-a8f7-a5c832e9aa7f", "bot": false, "x": 227.18, "y": 36.61, "z": 175.22, "ts": 1770709410, "e": "Position"}, {"uid": "81d929b0-7372-44f6-a8f7-a5c832e9aa7f", "bot": false, "x": 226.77, "y": 36.61, "z": 174.21, "ts": 1770709415, "e": "Loot"}, {"uid": "81d929b0-7372-44f6-a8f7-a5c832e9aa7f", "bot": false, "x": 226.77, "y": 36.61, "z": 174.21, "ts": 1770709415, "e": "Position"}, {"uid": "81d929b0-7372-44f6-a8f7-a5c832e9aa7f", "bot": false, "x": 235.23, "y": 36.61, "z": 183.23, "ts": 1770709420, "e": "Position"}, {"uid": "81d929b0-7372-44f6-a8f7-a5c832e9aa7f", "bot": false, "x": 238.09, "y": 36.61, "z": 187.48, "ts": 1770709423, "e": "Loot"}, {"uid": "81d929b0-7372-44f6-a8f7-a5c832e9aa7f", "bot": false, "x": 239.3, "y": 36.61, "z": 186.2, "ts": 1770709425, "e": "Position"}, {"uid": "81d929b0-7372-44f6-a8f7-a5c832e9aa7f", "bot": false, "x": 247.58, "y": 36.63, "z": 182.19, "ts": 1770709430, "e": "Position"}, {"uid": "81d929b0-7372-44f6-a8f7-a5c832e9aa7f", "bot": false, "x": 249.02, "y": 36.62, "z": 176.13, "ts": 1770709435, "e": "Position"}, {"uid": "81d929b0-7372-44f6-a8f7-a5c832e9aa7f", "bot": false, "x": 249.55, "y": 36.62, "z": 175.57, "ts": 1770709439, "e": "Loot"}, {"uid": "81d929b0-7372-44f6-a8f7-a5c832e9aa7f", "bot": false, "x": 227.24, "y": 36.59, "z": 178.37, "ts": 1770709445, "e": "Position"}, {"uid": "81d929b0-7372-44f6-a8f7-a5c832e9aa7f", "bot": false, "x": 227.3, "y": 36.59, "z": 178.6, "ts": 1770709449, "e": "Loot"}, {"uid": "81d929b0-7372-44f6-a8f7-a5c832e9aa7f", "bot": false, "x": 218.24, "y": 36.86, "z": 180.12, "ts": 1770709455, "e": "Position"}, {"uid": "81d929b0-7372-44f6-a8f7-a5c832e9aa7f", "bot": false, "x": 222.14, "y": 36.57, "z": 177.23, "ts": 1770709460, "e": "Position"}, {"uid": "81d929b0-7372-44f6-a8f7-a5c832e9aa7f", "bot": false, "x": 236.95, "y": 37.04, "z": 162.46, "ts": 1770709470, "e": "Position"}, {"uid": "81d929b0-7372-44f6-a8f7-a5c832e9aa7f", "bot": false, "x": 246.82, "y": 39.74, "z": 148.18, "ts": 1770709475, "e": "Position"}, {"uid": "81d929b0-7372-44f6-a8f7-a5c832e9aa7f", "bot": false, "x": 251.6, "y": 39.93, "z": 130.11, "ts": 1770709480, "e": "Position"}, {"uid": "81d929b0-7372-44f6-a8f7-a5c832e9aa7f", "bot": false, "x": 252.56, "y": 39.96, "z": 112.28, "ts": 1770709485, "e": "Position"}, {"uid": "81d929b0-7372-44f6-a8f7-a5c832e9aa7f", "bot": false, "x": 234.02, "y": 41.54, "z": 106.02, "ts": 1770709490, "e": "Position"}, {"uid": "81d929b0-7372-44f6-a8f7-a5c832e9aa7f", "bot": false, "x": 253.7, "y": 42.21, "z": 86.13, "ts": 1770709495, "e": "Position"}, {"uid": "81d929b0-7372-44f6-a8f7-a5c832e9aa7f", "bot": false, "x": 250.44, "y": 42.21, "z": 76.26, "ts": 1770709500, "e": "Position"}, {"uid": "81d929b0-7372-44f6-a8f7-a5c832e9aa7f", "bot": false, "x": 250.44, "y": 42.21, "z": 76.26, "ts": 1770709500, "e": "Loot"}, {"uid": "81d929b0-7372-44f6-a8f7-a5c832e9aa7f", "bot": false, "x": 250.44, "y": 42.21, "z": 76.26, "ts": 1770709500, "e": "Loot"}, {"uid": "81d929b0-7372-44f6-a8f7-a5c832e9aa7f", "bot": false, "x": 250.93, "y": 42.21, "z": 73.68, "ts": 1770709504, "e": "Loot"}, {"uid": "81d929b0-7372-44f6-a8f7-a5c832e9aa7f", "bot": false, "x": 251.99, "y": 42.21, "z": 71.62, "ts": 1770709505, "e": "Position"}, {"uid": "81d929b0-7372-44f6-a8f7-a5c832e9aa7f", "bot": false, "x": 259.86, "y": 42.21, "z": 62.89, "ts": 1770709510, "e": "Position"}, {"uid": "81d929b0-7372-44f6-a8f7-a5c832e9aa7f", "bot": false, "x": 263.83, "y": 42.38, "z": 53.45, "ts": 1770709514, "e": "Loot"}, {"uid": "81d929b0-7372-44f6-a8f7-a5c832e9aa7f", "bot": false, "x": 267.06, "y": 42.38, "z": 52.07, "ts": 1770709515, "e": "Position"}, {"uid": "81d929b0-7372-44f6-a8f7-a5c832e9aa7f", "bot": false, "x": 270.93, "y": 42.38, "z": 47.88, "ts": 1770709517, "e": "Loot"}, {"uid": "81d929b0-7372-44f6-a8f7-a5c832e9aa7f", "bot": false, "x": 270.81, "y": 42.38, "z": 53.76, "ts": 1770709520, "e": "Position"}, {"uid": "81d929b0-7372-44f6-a8f7-a5c832e9aa7f", "bot": false, "x": 273.4, "y": 42.19, "z": 45.97, "ts": 1770709530, "e": "Position"}, {"uid": "81d929b0-7372-44f6-a8f7-a5c832e9aa7f", "bot": false, "x": 268.65, "y": 42.38, "z": 48.02, "ts": 1770709546, "e": "Position"}, {"uid": "81d929b0-7372-44f6-a8f7-a5c832e9aa7f", "bot": false, "x": 274.28, "y": 42.24, "z": 46.36, "ts": 1770709551, "e": "Position"}, {"uid": "81d929b0-7372-44f6-a8f7-a5c832e9aa7f", "bot": false, "x": 260.44, "y": 43.41, "z": 34.3, "ts": 1770709556, "e": "Position"}, {"uid": "81d929b0-7372-44f6-a8f7-a5c832e9aa7f", "bot": false, "x": 260.63, "y": 48.6, "z": 25.35, "ts": 1770709561, "e": "Position"}, {"uid": "81d929b0-7372-44f6-a8f7-a5c832e9aa7f", "bot": false, "x": 249.16, "y": 48.6, "z": 28.74, "ts": 1770709566, "e": "Position"}, {"uid": "81d929b0-7372-44f6-a8f7-a5c832e9aa7f", "bot": false, "x": 241.97, "y": 48.58, "z": 36.43, "ts": 1770709570, "e": "Loot"}, {"uid": "81d929b0-7372-44f6-a8f7-a5c832e9aa7f", "bot": false, "x": 243.23, "y": 48.58, "z": 36.44, "ts": 1770709571, "e": "Position"}, {"uid": "81d929b0-7372-44f6-a8f7-a5c832e9aa7f", "bot": false, "x": 253.09, "y": 48.58, "z": 37.7, "ts": 1770709574, "e": "Loot"}, {"uid": "81d929b0-7372-44f6-a8f7-a5c832e9aa7f", "bot": false, "x": 253.17, "y": 48.58, "z": 35.1, "ts": 1770709576, "e": "Position"}, {"uid": "81d929b0-7372-44f6-a8f7-a5c832e9aa7f", "bot": false, "x": 241.55, "y": 48.58, "z": 14.6, "ts": 1770709581, "e": "Position"}, {"uid": "81d929b0-7372-44f6-a8f7-a5c832e9aa7f", "bot": false, "x": 240.94, "y": 48.58, "z": 14.33, "ts": 1770709583, "e": "Loot"}, {"uid": "81d929b0-7372-44f6-a8f7-a5c832e9aa7f", "bot": false, "x": 236.15, "y": 48.58, "z": 13.6, "ts": 1770709586, "e": "Position"}, {"uid": "81d929b0-7372-44f6-a8f7-a5c832e9aa7f", "bot": false, "x": 236.79, "y": 42.79, "z": -7.34, "ts": 1770709591, "e": "Position"}, {"uid": "81d929b0-7372-44f6-a8f7-a5c832e9aa7f", "bot": false, "x": 240.01, "y": 37.68, "z": -13.45, "ts": 1770709616, "e": "Position"}, {"uid": "81d929b0-7372-44f6-a8f7-a5c832e9aa7f", "bot": false, "x": 238.85, "y": 34.26, "z": -30.27, "ts": 1770709621, "e": "Position"}, {"uid": "81d929b0-7372-44f6-a8f7-a5c832e9aa7f", "bot": false, "x": 264.98, "y": 37.38, "z": -42.47, "ts": 1770709626, "e": "Position"}, {"uid": "81d929b0-7372-44f6-a8f7-a5c832e9aa7f", "bot": false, "x": 295.36, "y": 35.65, "z": -33.45, "ts": 1770709631, "e": "Position"}, {"uid": "81d929b0-7372-44f6-a8f7-a5c832e9aa7f", "bot": false, "x": 315.25, "y": 35.17, "z": -7.76, "ts": 1770709636, "e": "Position"}, {"uid": "81d929b0-7372-44f6-a8f7-a5c832e9aa7f", "bot": false, "x": 317.06, "y": 35.1, "z": 13.35, "ts": 1770709641, "e": "Position"}, {"uid": "81d929b0-7372-44f6-a8f7-a5c832e9aa7f", "bot": false, "x": 316.87, "y": 35.1, "z": 14.22, "ts": 1770709642, "e": "Loot"}, {"uid": "81d929b0-7372-44f6-a8f7-a5c832e9aa7f", "bot": false, "x": 319.74, "y": 35.14, "z": 33.02, "ts": 1770709646, "e": "Position"}, {"uid": "81d929b0-7372-44f6-a8f7-a5c832e9aa7f", "bot": false, "x": 328.01, "y": 35.36, "z": 64.53, "ts": 1770709651, "e": "Position"}, {"uid": "81d929b0-7372-44f6-a8f7-a5c832e9aa7f", "bot": false, "x": 327.86, "y": 35.45, "z": 85.22, "ts": 1770709656, "e": "Position"}, {"uid": "81d929b0-7372-44f6-a8f7-a5c832e9aa7f", "bot": false, "x": 318.85, "y": 36.54, "z": 114.89, "ts": 1770709661, "e": "Position"}, {"uid": "81d929b0-7372-44f6-a8f7-a5c832e9aa7f", "bot": false, "x": 307.9, "y": 36.38, "z": 120.62, "ts": 1770709666, "e": "Position"}, {"uid": "81d929b0-7372-44f6-a8f7-a5c832e9aa7f", "bot": false, "x": 319.26, "y": 36.61, "z": 117.29, "ts": 1770709671, "e": "Position"}, {"uid": "81d929b0-7372-44f6-a8f7-a5c832e9aa7f", "bot": false, "x": 316.57, "y": 36.42, "z": 110.46, "ts": 1770709676, "e": "Position"}, {"uid": "81d929b0-7372-44f6-a8f7-a5c832e9aa7f", "bot": false, "x": 314.61, "y": 36.42, "z": 111.1, "ts": 1770709681, "e": "Position"}]