[{"uid": "f7d38dff-74d4-45d3-a39e-2c38bbd7c10e", "bot": false, "x": 251.12, "y": 11.6, "z": -45.35, "ts": 1770907605, "e": "Position"}, {"uid": "f7d38dff-74d4-45d3-a39e-2c38bbd7c10e", "bot": false, "x": 233.6, "y": 14.78, "z": -29.3, "ts": 1770907625, "e": "Position"}, {"uid": "f7d38dff-74d4-45d3-a39e-2c38bbd7c10e", "bot": false, "x": 235.97, "y": 16.1, "z": -21.38, "ts": 1770907628, "e": "Loot"}, {"uid": "f7d38dff-74d4-45d3-a39e-2c38bbd7c10e", "bot": false, "x": 232.89, "y": 16.31, "z": -20.58, "ts": 1770907630, "e": "Position"}, {"uid": "f7d38dff-74d4-45d3-a39e-2c38bbd7c10e", "bot": false, "x": 232.89, "y": 16.31, "z": -20.58, "ts": 1770907633, "e": "Loot"}, {"uid": "f7d38dff-74d4-45d3-a39e-2c38bbd7c10e", "bot": false, "x": 232.89, "y": 16.31, "z": -20.58, "ts": 1770907633, "e": "Loot"}, {"uid": "f7d38dff-74d4-45d3-a39e-2c38bbd7c10e", "bot": false, "x": 232.89, "y": 16.31, "z": -20.58, "ts": 1770907634, "e": "Loot"}, {"uid": "f7d38dff-74d4-45d3-a39e-2c38bbd7c10e", "bot": false, "x": 233.19, "y": 16.31, "z": -19.11, "ts": 1770907635, "e": "Position"}, {"uid": "f7d38dff-74d4-45d3-a39e-2c38bbd7c10e", "bot": false, "x": 213.76, "y": 21.05, "z": -24.06, "ts": 1770907640, "e": "Position"}, {"uid": "f7d38dff-74d4-45d3-a39e-2c38bbd7c10e", "bot": false, "x": 202.08, "y": 21.1, "z": -28.76, "ts": 1770907645, "e": "Position"}, {"uid": "f7d38dff-74d4-45d3-a39e-2c38bbd7c10e", "bot": false, "x": 202.08, "y": 21.1, "z": -28.76, "ts": 1770907646, "e": "Loot"}, {"uid": "f7d38dff-74d4-45d3-a39e-2c38bbd7c10e", "bot": false, "x": 201.42, "y": 21.1, "z": -39.76, "ts": 1770907650, "e": "Position"}, {"uid": "f7d38dff-74d4-45d3-a39e-2c38bbd7c10e", "bot": false, "x": 200.43, "y": 21.1, "z": -37.6, "ts": 1770907653, "e": "Loot"}, {"uid": "f7d38dff-74d4-45d3-a39e-2c38bbd7c10e", "bot": false, "x": 193.76, "y": 21.02, "z": -37.03, "ts": 1770907655, "e": "Position"}, {"uid": "f7d38dff-74d4-45d3-a39e-2c38bbd7c10e", "bot": false, "x": 186.09, "y": 21.18, "z": -20.77, "ts": 1770907660, "e": "Position"}, {"uid": "f7d38dff-74d4-45d3-a39e-2c38bbd7c10e", "bot": false, "x": 178.25, "y": 21.18, "z": -19.94, "ts": 1770907665, "e": "Position"}, {"uid": "f7d38dff-74d4-45d3-a39e-2c38bbd7c10e", "bot": false, "x": 179.63, "y": 21.19, "z": -29.58, "ts": 1770907670, "e": "Position"}, {"uid": "f7d38dff-74d4-45d3-a39e-2c38bbd7c10e", "bot": false, "x": 173.4, "y": 21.19, "z": -28.72, "ts": 1770907675, "e": "Position"}, {"uid": "f7d38dff-74d4-45d3-a39e-2c38bbd7c10e", "bot": false, "x": 167.64, "y": 21.02, "z": -19.21, "ts": 1770907680, "e": "Position"}, {"uid": "f7d38dff-74d4-45d3-a39e-2c38bbd7c10e", "bot": false, "x": 161.28, "y": 21.02, "z": -47.24, "ts": 1770907685, "e": "Position"}, {"uid": "f7d38dff-74d4-45d3-a39e-2c38bbd7c10e", "bot": false, "x": 169.88, "y": 23.49, "z": -62.73, "ts": 1770907690, "e": "Position"}, {"uid": "f7d38dff-74d4-45d3-a39e-2c38bbd7c10e", "bot": false, "x": 181.44, "y": 23.56, "z": -60.37, "ts": 1770907695, "e": "Position"}, {"uid": "f7d38dff-74d4-45d3-a39e-2c38bbd7c10e", "bot": false, "x": 195.79, "y": 23.49, "z": -71.3, "ts": 1770907700, "e": "Position"}, {"uid": "f7d38dff-74d4-45d3-a39e-2c38bbd7c10e", "bot": false, "x": 193.89, "y": 23.49, "z": -72.23, "ts": 1770907705, "e": "Position"}, {"uid": "f7d38dff-74d4-45d3-a39e-2c38bbd7c10e", "bot": false, "x": 193.9, "y": 27.0, "z": -69.88, "ts": 1770907710, "e": "Position"}, {"uid": "f7d38dff-74d4-45d3-a39e-2c38bbd7c10e", "bot": false, "x": 184.79, "y": 23.48, "z": -56.45, "ts": 1770907715, "e": "Position"}, {"uid": "f7d38dff-74d4-45d3-a39e-2c38bbd7c10e", "bot": false, "x": 206.43, "y": 21.08, "z": -57.03, "ts": 1770907721, "e": "Position"}, {"uid": "f7d38dff-74d4-45d3-a39e-2c38bbd7c10e", "bot": false, "x": 203.69, "y": 21.1, "z": -39.53, "ts": 1770907726, "e": "Position"}, {"uid": "f7d38dff-74d4-45d3-a39e-2c38bbd7c10e", "bot": false, "x": 197.0, "y": 21.03, "z": -21.16, "ts": 1770907736, "e": "Position"}, {"uid": "f7d38dff-74d4-45d3-a39e-2c38bbd7c10e", "bot": false, "x": 183.02, "y": 21.26, "z": 1.34, "ts": 1770907741, "e": "Position"}, {"uid": "f7d38dff-74d4-45d3-a39e-2c38bbd7c10e", "bot": false, "x": 168.34, "y": 25.9, "z": 23.24, "ts": 1770907746, "e": "Position"}, {"uid": "f7d38dff-74d4-45d3-a39e-2c38bbd7c10e", "bot": false, "x": 143.58, "y": 27.4, "z": 28.41, "ts": 1770907751, "e": "Position"}, {"uid": "f7d38dff-74d4-45d3-a39e-2c38bbd7c10e", "bot": false, "x": 123.42, "y": 29.02, "z": 6.22, "ts": 1770907756, "e": "Position"}, {"uid": "f7d38dff-74d4-45d3-a39e-2c38bbd7c10e", "bot": false, "x": 101.57, "y": 31.03, "z": 6.82, "ts": 1770907761, "e": "Position"}, {"uid": "f7d38dff-74d4-45d3-a39e-2c38bbd7c10e", "bot": false, "x": 101.57, "y": 31.03, "z": 6.82, "ts": 1770907762, "e": "Loot"}, {"uid": "f7d38dff-74d4-45d3-a39e-2c38bbd7c10e", "bot": false, "x": 85.92, "y": 27.84, "z": -0.25, "ts": 1770907766, "e": "Position"}, {"uid": "f7d38dff-74d4-45d3-a39e-2c38bbd7c10e", "bot": false, "x": 62.08, "y": 28.84, "z": 3.01, "ts": 1770907771, "e": "Position"}, {"uid": "f7d38dff-74d4-45d3-a39e-2c38bbd7c10e", "bot": false, "x": 48.3, "y": 31.12, "z": 21.04, "ts": 1770907776, "e": "Position"}, {"uid": "f7d38dff-74d4-45d3-a39e-2c38bbd7c10e", "bot": false, "x": 34.72, "y": 28.16, "z": 25.54, "ts": 1770907781, "e": "Position"}, {"uid": "f7d38dff-74d4-45d3-a39e-2c38bbd7c10e", "bot": false, "x": 39.63, "y": 29.01, "z": 17.6, "ts": 1770907786, "e": "Position"}, {"uid": "f7d38dff-74d4-45d3-a39e-2c38bbd7c10e", "bot": false, "x": 39.5, "y": 28.03, "z": 2.22, "ts": 1770907791, "e": "Position"}, {"uid": "f7d38dff-74d4-45d3-a39e-2c38bbd7c10e", "bot": false, "x": 52.0, "y": 28.77, "z": 6.04, "ts": 1770907795, "e": "Loot"}, {"uid": "f7d38dff-74d4-45d3-a39e-2c38bbd7c10e", "bot": false, "x": 52.0, "y": 28.77, "z": 6.04, "ts": 1770907796, "e": "Position"}, {"uid": "f7d38dff-74d4-45d3-a39e-2c38bbd7c10e", "bot": false, "x": 51.67, "y": 28.8, "z": 6.09, "ts": 1770907796, "e": "Loot"}, {"uid": "f7d38dff-74d4-45d3-a39e-2c38bbd7c10e", "bot": false, "x": 57.69, "y": 28.85, "z": 2.57, "ts": 1770907801, "e": "Position"}, {"uid": "f7d38dff-74d4-45d3-a39e-2c38bbd7c10e", "bot": false, "x": 57.69, "y": 28.85, "z": 2.57, "ts": 1770907802, "e": "Loot"}, {"uid": "f7d38dff-74d4-45d3-a39e-2c38bbd7c10e", "bot": false, "x": 47.38, "y": 25.73, "z": -6.9, "ts": 1770907806, "e": "Position"}, {"uid": "f7d38dff-74d4-45d3-a39e-2c38bbd7c10e", "bot": false, "x": 35.32, "y": 21.11, "z": -30.63, "ts": 1770907811, "e": "Position"}, {"uid": "f7d38dff-74d4-45d3-a39e-2c38bbd7c10e", "bot": false, "x": 40.82, "y": 18.83, "z": -45.94, "ts": 1770907816, "e": "Position"}, {"uid": "f7d38dff-74d4-45d3-a39e-2c38bbd7c10e", "bot": false, "x": 22.19, "y": 12.86, "z": -30.74, "ts": 1770907821, "e": "Position"}, {"uid": "f7d38dff-74d4-45d3-a39e-2c38bbd7c10e", "bot": false, "x": 19.41, "y": 11.62, "z": -35.3, "ts": 1770907826, "e": "Position"}, {"uid": "f7d38dff-74d4-45d3-a39e-2c38bbd7c10e", "bot": false, "x": -3.25, "y": 8.47, "z": -50.68, "ts": 1770907831, "e": "Position"}, {"uid": "f7d38dff-74d4-45d3-a39e-2c38bbd7c10e", "bot": false, "x": -11.8, "y": 9.74, "z": -63.92, "ts": 1770907834, "e": "BotKill"}, {"uid": "f7d38dff-74d4-45d3-a39e-2c38bbd7c10e", "bot": false, "x": -13.58, "y": 9.57, "z": -64.71, "ts": 1770907836, "e": "Position"}, {"uid": "f7d38dff-74d4-45d3-a39e-2c38bbd7c10e", "bot": false, "x": -14.58, "y": 9.27, "z": -64.68, "ts": 1770907837, "e": "Loot"}, {"uid": "f7d38dff-74d4-45d3-a39e-2c38bbd7c10e", "bot": false, "x": -14.35, "y": 9.36, "z": -64.81, "ts": 1770907838, "e": "Loot"}, {"uid": "f7d38dff-74d4-45d3-a39e-2c38bbd7c10e", "bot": false, "x": -16.77, "y": 9.14, "z": -63.99, "ts": 1770907841, "e": "Position"}, {"uid": "f7d38dff-74d4-45d3-a39e-2c38bbd7c10e", "bot": false, "x": -25.05, "y": 9.14, "z": -63.64, "ts": 1770907846, "e": "Position"}, {"uid": "f7d38dff-74d4-45d3-a39e-2c38bbd7c10e", "bot": false, "x": -21.03, "y": 9.14, "z": -64.35, "ts": 1770907850, "e": "BotKill"}, {"uid": "f7d38dff-74d4-45d3-a39e-2c38bbd7c10e", "bot": false, "x": -20.1, "y": 9.14, "z": -64.68, "ts": 1770907851, "e": "Position"}, {"uid": "f7d38dff-74d4-45d3-a39e-2c38bbd7c10e", "bot": false, "x": -14.68, "y": 9.27, "z": -65.04, "ts": 1770907853, "e": "BotKill"}, {"uid": "f7d38dff-74d4-45d3-a39e-2c38bbd7c10e", "bot": false, "x": -13.04, "y": 9.98, "z": -67.25, "ts": 1770907856, "e": "Position"}, {"uid": "f7d38dff-74d4-45d3-a39e-2c38bbd7c10e", "bot": false, "x": -11.9, "y": 9.7, "z": -63.33, "ts": 1770907860, "e": "BotKill"}, {"uid": "f7d38dff-74d4-45d3-a39e-2c38bbd7c10e", "bot": false, "x": -12.45, "y": 9.44, "z": -62.21, "ts": 1770907861, "e": "Position"}, {"uid": "f7d38dff-74d4-45d3-a39e-2c38bbd7c10e", "bot": false, "x": -17.91, "y": 9.12, "z": -63.63, "ts": 1770907866, "e": "Position"}, {"uid": "f7d38dff-74d4-45d3-a39e-2c38bbd7c10e", "bot": false, "x": -20.22, "y": 9.12, "z": -63.81, "ts": 1770907870, "e": "Loot"}, {"uid": "f7d38dff-74d4-45d3-a39e-2c38bbd7c10e", "bot": false, "x": -20.22, "y": 9.12, "z": -63.81, "ts": 1770907871, "e": "Loot"}, {"uid": "f7d38dff-74d4-45d3-a39e-2c38bbd7c10e", "bot": false, "x": -20.35, "y": 9.12, "z": -63.8, "ts": 1770907871, "e": "Position"}, {"uid": "f7d38dff-74d4-45d3-a39e-2c38bbd7c10e", "bot": false, "x": -25.82, "y": 9.12, "z": -62.84, "ts": 1770907876, "e": "Position"}, {"uid": "f7d38dff-74d4-45d3-a39e-2c38bbd7c10e", "bot": false, "x": -25.82, "y": 9.12, "z": -62.84, "ts": 1770907879, "e": "Loot"}, {"uid": "f7d38dff-74d4-45d3-a39e-2c38bbd7c10e", "bot": false, "x": -25.82, "y": 9.12, "z": -62.84, "ts": 1770907880, "e": "Loot"}, {"uid": "f7d38dff-74d4-45d3-a39e-2c38bbd7c10e", "bot": false, "x": -27.45, "y": 9.12, "z": -61.7, "ts": 1770907882, "e": "Loot"}, {"uid": "f7d38dff-74d4-45d3-a39e-2c38bbd7c10e", "bot": false, "x": -32.91, "y": 9.38, "z": -61.02, "ts": 1770907884, "e": "Loot"}, {"uid": "f7d38dff-74d4-45d3-a39e-2c38bbd7c10e", "bot": false, "x": -32.91, "y": 9.38, "z": -61.02, "ts": 1770907885, "e": "Loot"}, {"uid": "f7d38dff-74d4-45d3-a39e-2c38bbd7c10e", "bot": false, "x": -32.78, "y": 9.26, "z": -60.88, "ts": 1770907886, "e": "Loot"}, {"uid": "f7d38dff-74d4-45d3-a39e-2c38bbd7c10e", "bot": false, "x": -32.02, "y": 9.11, "z": -60.22, "ts": 1770907886, "e": "Position"}, {"uid": "f7d38dff-74d4-45d3-a39e-2c38bbd7c10e", "bot": false, "x": -26.82, "y": 9.11, "z": -62.38, "ts": 1770907889, "e": "Loot"}, {"uid": "f7d38dff-74d4-45d3-a39e-2c38bbd7c10e", "bot": false, "x": -29.35, "y": 9.11, "z": -60.93, "ts": 1770907891, "e": "Position"}, {"uid": "f7d38dff-74d4-45d3-a39e-2c38bbd7c10e", "bot": false, "x": -39.02, "y": 9.11, "z": -53.0, "ts": 1770907896, "e": "Position"}, {"uid": "f7d38dff-74d4-45d3-a39e-2c38bbd7c10e", "bot": false, "x": -39.02, "y": 9.11, "z": -53.0, "ts": 1770907898, "e": "Loot"}, {"uid": "f7d38dff-74d4-45d3-a39e-2c38bbd7c10e", "bot": false, "x": -29.19, "y": 9.11, "z": -50.33, "ts": 1770907902, "e": "Position"}, {"uid": "f7d38dff-74d4-45d3-a39e-2c38bbd7c10e", "bot": false, "x": -22.12, "y": 9.11, "z": -53.11, "ts": 1770907917, "e": "Position"}, {"uid": "f7d38dff-74d4-45d3-a39e-2c38bbd7c10e", "bot": false, "x": -26.21, "y": 9.11, "z": -46.7, "ts": 1770907922, "e": "Position"}, {"uid": "f7d38dff-74d4-45d3-a39e-2c38bbd7c10e", "bot": false, "x": -24.05, "y": 9.11, "z": -53.33, "ts": 1770907927, "e": "Position"}, {"uid": "f7d38dff-74d4-45d3-a39e-2c38bbd7c10e", "bot": false, "x": -34.27, "y": 9.11, "z": -54.04, "ts": 1770907937, "e": "Position"}, {"uid": "f7d38dff-74d4-45d3-a39e-2c38bbd7c10e", "bot": false, "x": -27.35, "y": 9.11, "z": -38.62, "ts": 1770907942, "e": "Position"}, {"uid": "f7d38dff-74d4-45d3-a39e-2c38bbd7c10e", "bot": false, "x": -21.95, "y": 8.93, "z": -24.18, "ts": 1770907947, "e": "Position"}, {"uid": "f7d38dff-74d4-45d3-a39e-2c38bbd7c10e", "bot": false, "x": -20.27, "y": 8.86, "z": -31.51, "ts": 1770907952, "e": "Position"}, {"uid": "f7d38dff-74d4-45d3-a39e-2c38bbd7c10e", "bot": false, "x": -34.16, "y": 9.11, "z": -48.41, "ts": 1770907957, "e": "Position"}, {"uid": "f7d38dff-74d4-45d3-a39e-2c38bbd7c10e", "bot": false, "x": -25.79, "y": 9.11, "z": -45.96, "ts": 1770907961, "e": "Loot"}, {"uid": "f7d38dff-74d4-45d3-a39e-2c38bbd7c10e", "bot": false, "x": -25.79, "y": 9.11, "z": -45.96, "ts": 1770907962, "e": "Position"}, {"uid": "f7d38dff-74d4-45d3-a39e-2c38bbd7c10e", "bot": false, "x": -25.79, "y": 9.11, "z": -45.96, "ts": 1770907962, "e": "Loot"}, {"uid": "f7d38dff-74d4-45d3-a39e-2c38bbd7c10e", "bot": false, "x": -25.79, "y": 9.11, "z": -45.96, "ts": 1770907963, "e": "Loot"}, {"uid": "f7d38dff-74d4-45d3-a39e-2c38bbd7c10e", "bot": false, "x": -25.79, "y": 9.11, "z": -45.96, "ts": 1770907963, "e": "Loot"}, {"uid": "f7d38dff-74d4-45d3-a39e-2c38bbd7c10e", "bot": false, "x": -32.1, "y": 9.11, "z": -54.31, "ts": 1770907967, "e": "Position"}, {"uid": "f7d38dff-74d4-45d3-a39e-2c38bbd7c10e", "bot": false, "x": -38.92, "y": 9.11, "z": -40.19, "ts": 1770907972, "e": "Position"}, {"uid": "f7d38dff-74d4-45d3-a39e-2c38bbd7c10e", "bot": false, "x": -37.91, "y": 9.11, "z": -36.16, "ts": 1770907981, "e": "BotKill"}, {"uid": "f7d38dff-74d4-45d3-a39e-2c38bbd7c10e", "bot": false, "x": -37.49, "y": 9.11, "z": -34.94, "ts": 1770907982, "e": "Position"}, {"uid": "f7d38dff-74d4-45d3-a39e-2c38bbd7c10e", "bot": false, "x": -22.01, "y": 9.11, "z": -32.61, "ts": 1770907987, "e": "Position"}, {"uid": "f7d38dff-74d4-45d3-a39e-2c38bbd7c10e", "bot": false, "x": -6.81, "y": 8.68, "z": -52.14, "ts": 1770907992, "e": "Position"}, {"uid": "f7d38dff-74d4-45d3-a39e-2c38bbd7c10e", "bot": false, "x": -0.65, "y": 13.68, "z": -73.96, "ts": 1770907997, "e": "Position"}, {"uid": "f7d38dff-74d4-45d3-a39e-2c38bbd7c10e", "bot": false, "x": 8.89, "y": 16.02, "z": -94.25, "ts": 1770908002, "e": "Position"}, {"uid": "f7d38dff-74d4-45d3-a39e-2c38bbd7c10e", "bot": false, "x": 11.35, "y": 14.78, "z": -121.29, "ts": 1770908007, "e": "Position"}, {"uid": "f7d38dff-74d4-45d3-a39e-2c38bbd7c10e", "bot": false, "x": 20.69, "y": 14.17, "z": -151.37, "ts": 1770908012, "e": "Position"}, {"uid": "f7d38dff-74d4-45d3-a39e-2c38bbd7c10e", "bot": false, "x": 50.15, "y": 17.35, "z": -158.27, "ts": 1770908017, "e": "Position"}, {"uid": "f7d38dff-74d4-45d3-a39e-2c38bbd7c10e", "bot": false, "x": 78.15, "y": 23.28, "z": -143.47, "ts": 1770908022, "e": "Position"}, {"uid": "f7d38dff-74d4-45d3-a39e-2c38bbd7c10e", "bot": false, "x": 99.18, "y": 23.6, "z": -133.78, "ts": 1770908027, "e": "Position"}]